LICENSE
MANIFEST.in
README.md
setup.py
bin/demo.py
bin/webmention-tools
webmentiontools/__init__.py
webmentiontools/__init__.pyc
webmentiontools/send.py
webmentiontools/urlinfo.py
webmentiontools/webmentionio.py
webmentiontools.egg-info/PKG-INFO
webmentiontools.egg-info/SOURCES.txt
webmentiontools.egg-info/dependency_links.txt
webmentiontools.egg-info/requires.txt
webmentiontools.egg-info/top_level.txt