Metadata-Version: 1.0
Name: webmentiontools
Version: 0.3.1
Summary: Tools for webmention.org.
Home-page: https://github.com/vrypan/webmention-tools
Author: Panayotis Vryonis
Author-email: vrypan@gmail.com
License: LICENSE
Platform: UNKNOWN
